LICENSE
MANIFEST.in
README.md
requirements.txt
setup.cfg
setup.py
stdeb.cfg
./ekca_service/__about__.py
./ekca_service/__init__.py
./ekca_service/cmd.py
./ekca_service/settings.py
./ekca_service/srv.py
./ekca_service/sshca.py
./ekca_service/test.py
./ekca_service/plugins/__init__.py
./ekca_service/plugins/otp/__init__.py
./ekca_service/plugins/otp/base.py
./ekca_service/plugins/password/__init__.py
./ekca_service/plugins/password/base.py
ekca_service.egg-info/PKG-INFO
ekca_service.egg-info/SOURCES.txt
ekca_service.egg-info/dependency_links.txt
ekca_service.egg-info/entry_points.txt
ekca_service.egg-info/namespace_packages.txt
ekca_service.egg-info/not-zip-safe
ekca_service.egg-info/requires.txt
ekca_service.egg-info/top_level.txt
instance/ekca-demo.ae-dir.com.cfg
instance/ekca-stderr-logging.conf
instance/ekca-syslog-logging.conf