Metadata-Version: 2.1
Name: ekca-service
Version: 1.1.0
Summary: EKCA service
Home-page: https://ekca.stroeder.com
Author: Michael Stroeder
Author-email: michael@stroeder.com
Maintainer: Michael Stroeder
Maintainer-email: michael@stroeder.com
License: Apache-2.0
Download-URL: https://pypi.python.org/pypi/ekca-service
Keywords: PKI,SSH,SSH-CA,Certificate
Platform: UNKNOWN
Classifier: Development Status :: 5 - Production/Stable
Classifier: Environment :: No Input/Output (Daemon)
Classifier: Framework :: Flask
Classifier: Intended Audience :: Information Technology
Classifier: Intended Audience :: System Administrators
Classifier: License :: OSI Approved :: Apache Software License
Classifier: Operating System :: OS Independent
Classifier: Programming Language :: Python
Classifier: Programming Language :: Python :: 3
Classifier: Programming Language :: Python :: 3.6
Classifier: Programming Language :: Python :: 3.7
Classifier: Programming Language :: Python :: 3.8
Classifier: Programming Language :: Python :: 3.9
Classifier: Programming Language :: Python :: 3.10
Classifier: Programming Language :: Python :: 3 :: Only
Classifier: Topic :: System :: Systems Administration
Classifier: Topic :: System :: Systems Administration :: Authentication/Directory
Classifier: Topic :: System :: Systems Administration :: Authentication/Directory :: LDAP
Requires-Python: >=3.6.*
License-File: LICENSE
